bg_remover/__init__.py
bg_remover/remover.py
bg_remover11-0.3.dist-info/METADATA
bg_remover11-0.3.dist-info/WHEEL
bg_remover11-0.3.dist-info/top_level.txt
bg_remover11-0.3.dist-info/RECORD
