Metadata-Version: 2.1
Name: bg-remover11
Version: 0.3
Requires-Dist: rembg
Requires-Dist: Pillow
